{
  "total_pdf": 1473,
  "parsed": 1473,
  "failed": 0,
  "roles": 7656,
  "lines": 360223,
  "role_label_coverage": {
    "有行当标注剧目": 1471,
    "无行当标注剧目": 2
  },
  "no_scene_plays": 0,
  "big_type_dist": {
    "生": 2944,
    "净": 1631,
    "旦": 1578,
    "丑": 1194,
    "末": 243,
    "杂": 66
  },
  "by_collection": {
    "《戏考》": 448,
    "《京剧汇编》": 360,
    "《国剧大成》": 194,
    "《京剧丛刊》": 71,
    "《传统剧目汇编》": 67,
    "俞振飞剧本选": 45,
    "录音、唱片本": 34,
    "李洪春剧本选": 27,
    "《戏典》": 25,
    "侯玉山剧本选": 20,
    "荀慧生剧本选": 15,
    "周信芳剧本选": 14,
    "汪笑侬剧本选": 14,
    "孟小冬剧本选": 12,
    "程砚秋剧本选": 12,
    "名家藏本、演出本": 11,
    "梅兰芳剧本选": 11,
    "唐韵笙剧本选": 10,
    "萧长华剧本选": 9,
    "马连良剧本选": 9,
    "《京剧流派剧目荟萃》": 8,
    "《剧学月刊》": 7,
    "翁偶虹剧本选": 6,
    "院团改编本、演出本": 6,
    "方荣翔剧本选": 5,
    "郝寿臣剧本选": 5,
    "马祥麟剧本选": 5,
    "《京剧集成》": 4,
    "田汉剧本选": 4,
    "《戏考大全》": 3,
    "《中国传统戏曲剧本选集》": 2,
    "《传统戏曲剧目资料汇编》": 2,
    "欧阳予倩剧本选": 2,
    "老舍剧本选": 2,
    "《大众戏曲丛书》": 1,
    "侯少奎剧本选": 1,
    "范钧宏、吕瑞明剧本选": 1,
    "范钧宏剧本选": 1
  },
  "failed_samples": []
}